LICENSE.txt
MANIFEST.in
README.md
pypi_full.rst
requirements.txt
setup.cfg
CAMSA-1.3.data/scripts/agouti2camsa_points.py
CAMSA-1.3.data/scripts/agp2camsa_points.py
CAMSA-1.3.data/scripts/camsa_points2fasta.py
CAMSA-1.3.data/scripts/fasta2camsa_points.py
CAMSA-1.3.data/scripts/fasta2camsa_seqi.py
CAMSA-1.3.data/scripts/grimm2camsa_points.py
CAMSA-1.3.data/scripts/ragout_coords2camsa_points.py
CAMSA-1.3.data/scripts/ragout_coords2camsa_seqi.py
CAMSA-1.3.data/scripts/ragout_coords2fasta.py
CAMSA-1.3.data/scripts/ragout_coords_coverage.py
CAMSA-1.3.data/scripts/run_camsa.py
CAMSA-1.3.dist-info/METADATA
CAMSA-1.3.dist-info/RECORD
CAMSA-1.3.dist-info/WHEEL
CAMSA-1.3.dist-info/top_level.txt
CAMSA.egg-info/PKG-INFO
CAMSA.egg-info/SOURCES.txt
CAMSA.egg-info/dependency_links.txt
CAMSA.egg-info/requires.txt
CAMSA.egg-info/top_level.txt
camsa/__init__.py
camsa/logging.ini
camsa/run_camsa.ini
camsa/run_camsa.py
camsa/core/__init__.py
camsa/core/comparative_analysis.py
camsa/core/data_structures.py
camsa/core/io.py
camsa/core/merging.py
camsa/core/reference_analysis.py
camsa/examples/gage/exp1/contigs.fasta.gz
camsa/examples/gage/exp1/gam-ngs.camsa.points
camsa/examples/gage/exp1/metassembler.camsa.points
camsa/examples/gage/exp1/scaffmatch.camsa.points
camsa/examples/gage/exp1/sga.camsa.points
camsa/examples/gage/exp1/soap2.camsa.points
camsa/examples/gage/exp1/sspace.camsa.points
camsa/examples/gage/exp2/contigs.camsa.lengths
camsa/examples/gage/exp2/contigs.fasta.gz
camsa/examples/gage/exp2/gam-ngs.camsa.points
camsa/examples/gage/exp2/metassembler.camsa.points
camsa/examples/gage/exp2/scaffmatch.camsa.points
camsa/examples/gage/exp2/sga.camsa.points
camsa/examples/gage/exp2/soap2.camsa.points
camsa/examples/gage/exp2/sspace.camsa.points
camsa/examples/gage/exp3/gam-ngs.camsa.points
camsa/examples/gage/exp3/metassembler.camsa.points
camsa/examples/gage/exp3/scaffmatch.camsa.points
camsa/examples/gage/exp3/sga.camsa.points
camsa/examples/gage/exp3/soap2.camsa.points
camsa/examples/gage/exp3/sspace.camsa.points
camsa/examples/utils/agp/data/chr_from_component_wgs.agp
camsa/examples/utils/agp/data/chr_from_scaffold_wgs.agp
camsa/examples/utils/agp/data/scaffold_from_contig_wgs.agp
