Metadata-Version: 2.1
Name: CAMSA
Version: 1.3
Summary: CAMSA: a tool for Comparative Analysis and Merging of Scaffold Assemblies
Home-page: https://github.com/compbiol/camsa
Author: Sergey Aganezov
Author-email: aganezov@cs.jhu.edu
License: MIT
Keywords: comparative genomics,scaffolding,genome assembly
Platform: UNKNOWN
Classifier: Development Status :: 4 - Beta
Classifier: License :: OSI Approved :: MIT License
Classifier: Natural Language :: English
Classifier: Operating System :: MacOS
Classifier: Operating System :: Unix
Classifier: Topic :: Scientific/Engineering :: Bio-Informatics
Classifier: Programming Language :: Python :: 2
Classifier: Programming Language :: Python :: 2.7
Classifier: Programming Language :: Python :: 3
Classifier: Programming Language :: Python :: 3.5
Classifier: Programming Language :: Python :: 3.6
Classifier: Programming Language :: Python :: 3.7
Classifier: Intended Audience :: Science/Research
Classifier: Programming Language :: Python :: Implementation :: CPython
Requires-Dist: six (>=1.10.0)
Requires-Dist: networkx (>=2.1)
Requires-Dist: Jinja2 (>=2.8)
Requires-Dist: enum-compat
Requires-Dist: blist (>=1.3.6)
Requires-Dist: ConfigArgParse (>=0.10.0)
Requires-Dist: biopython (>=1.67)
Requires-Dist: bg (>=1.8.1)
Requires-Dist: more-itertools
